<?xml version="1.0" encoding="utf-8"?>
<AF xmlns:xsi="http://www.w3.org/2001/XMLSchema-instance" xsi:noNamespaceSchemaLocation="OSIsoft.AF.xsd" SchemaVersion="2.0" SoftwareVersion="2.10.0.8628" ExportMode="NoUniqueID" PISystem="PISRV01" Database="Lab Building Data" Description="" Created="2018-11-15T23:04:30.9659875Z" id="4768f92f-dbfd-4ca2-b186-46124a5fd1fe" ParentKey="4768f92f-dbfd-4ca2-b186-46124a5fd1fe" ExportedObject="NamedCollectionList" ExportedType="AFNamedCollectionList`1" Identity="EventFrame">
  <AFEventFrame>
    <Name>EF20181115-001</Name>
    <StartTime>2018-11-13T22:54:00Z</StartTime>
    <EndTime>2018-11-15T22:57:16Z</EndTime>
    <CanBeAcknowledged>false</CanBeAcknowledged>
    <AFElementRef>BLOCK1</AFElementRef>
  </AFEventFrame>
  <AFEventFrame>
    <Name>EF20181115-002</Name>
    <StartTime>2018-10-31T21:55:00Z</StartTime>
    <EndTime>2018-11-06T22:57:36Z</EndTime>
    <CanBeAcknowledged>false</CanBeAcknowledged>
    <AFElementRef>BLOCK1</AFElementRef>
  </AFEventFrame>
  <AFEventFrame>
    <Name>EF20181115-003</Name>
    <StartTime>2017-12-31T22:55:00Z</StartTime>
    <EndTime>2018-11-09T22:58:06Z</EndTime>
    <CanBeAcknowledged>false</CanBeAcknowledged>
    <AFElementRef>BLOCK1</AFElementRef>
  </AFEventFrame>
  <AFEventFrame>
    <Name>EF20181115-004</Name>
    <StartTime>2018-10-01T21:55:00Z</StartTime>
    <CanBeAcknowledged>false</CanBeAcknowledged>
    <AFElementRef>BLOCK2</AFElementRef>
  </AFEventFrame>
  <AFEventFrame>
    <Name>EF20181115-005</Name>
    <StartTime>2018-11-04T22:56:00Z</StartTime>
    <EndTime>2018-11-15T22:59:11Z</EndTime>
    <CanBeAcknowledged>false</CanBeAcknowledged>
    <AFElementRef>CONNECTED_INJECTOR4\BLOCK4</AFElementRef>
  </AFEventFrame>
  <AFEventFrame>
    <Name>EF20181115-006</Name>
    <StartTime>2018-11-13T22:56:00Z</StartTime>
    <EndTime>2018-11-14T22:59:11Z</EndTime>
    <CanBeAcknowledged>false</CanBeAcknowledged>
    <AFElementRef>CONNECTED_INJECTOR4\BLOCK4</AFElementRef>
  </AFEventFrame>
  <AFEventFrame>
    <Name>EF20181115-008</Name>
    <StartTime>2018-11-11T22:56:00Z</StartTime>
    <CanBeAcknowledged>false</CanBeAcknowledged>
    <AFElementRef>CONNECTED_INJECTOR4\BLOCK4</AFElementRef>
  </AFEventFrame>
  <AFEventFrame>
    <Name>EF20181115-009</Name>
    <StartTime>2018-11-11T22:56:00Z</StartTime>
    <EndTime>2018-11-13T22:59:11Z</EndTime>
    <CanBeAcknowledged>false</CanBeAcknowledged>
    <AFElementRef>CONNECTED_INJECTOR4\BLOCK4</AFElementRef>
  </AFEventFrame>
  <AFEventFrame>
    <Name>EF20181115-010</Name>
    <StartTime>2018-08-26T21:56:00Z</StartTime>
    <EndTime>2018-11-13T22:59:11Z</EndTime>
    <CanBeAcknowledged>false</CanBeAcknowledged>
    <AFElementRef>CONNECTED_INJECTOR4\BLOCK4</AFElementRef>
  </AFEventFrame>
</AF>